{
   "output_datafolder":"C:\\Users\\pielsticker\\Simulations\\",
   "name":"Mn_linear_combination_small_gas_phase",
   "labels":[
      "MnO",
      "Mn2O3",
      "MnO2"
   ],
   "spectra":[
      "Mn2p MnO",
      "Mn2p Mn2O3",
      "Mn2p MnO2"
   ],
   "input_filenames":{
      "reference_set_0":[
         "Mn2p_MnO.txt",
         "Mn2p_Mn2O3.txt",
         "Mn2p_MnO2.txt"
      ]
   },
   "no_of_simulations":50,
   "single":false,
   "variable_no_of_inputs":true,
   "always_auger":false,
   "always_core":true,
   "same_auger_core_percentage":true,
   "ensure_same_length":false,
   "eV_window":null,
   "normalize_inputs":true,
   "normalize_outputs":true,
   "broaden":true,
   "shift_x":true,
   "noise":true,
   "scatter":true,
   "sim_ranges":{
      "shift_x":[
         -3,
         3
      ],
      "noise":[
         3,
         35
      ],
      "FWHM":[
         0.5,
         2.0
      ],
      "scatterers":{
         "0":"He",
         "1":"H2",
         "2":"N2",
         "3":"O2"
      },
      "pressure":[
         0.1,
         0.5
      ],
      "distance":[
         0.1,
         1
      ]
   }
}